Metadata-Version: 2.1
Name: manna2
Version: 1.0
Summary:  An executor to launch encrypted bin files containing encrypted python code. Usage : from manna2 import *
Home-page: https://github.com/neelanjanmanna2021
Download-URL: https://github.com/user/reponame/archive/v_01.tar.gz
Author: Neelanjan Manna
Author-email: igi.manna@gmail.com
License: MIT
Keywords: steganography
Classifier: Development Status :: 3 - Alpha
Classifier: Intended Audience :: Developers
Classifier: Topic :: Software Development :: Build Tools
Classifier: License :: OSI Approved :: MIT License
Classifier: Programming Language :: Python :: 3
Classifier: Programming Language :: Python :: 3.4
Classifier: Programming Language :: Python :: 3.5
Classifier: Programming Language :: Python :: 3.6
Classifier: Programming Language :: Python :: 3.11
